linkgrid_x_transaction_id/__init__.py
linkgrid_x_transaction_id/constants.py
linkgrid_x_transaction_id/cubic_curve.py
linkgrid_x_transaction_id/interpolate.py
linkgrid_x_transaction_id/rotation.py
linkgrid_x_transaction_id/transaction.py
linkgrid_x_transaction_id/utils.py
linkgrid_x_transaction_id-1.0.1.dist-info/licenses/LICENSE
linkgrid_x_transaction_id-1.0.1.dist-info/METADATA
linkgrid_x_transaction_id-1.0.1.dist-info/WHEEL
linkgrid_x_transaction_id-1.0.1.dist-info/top_level.txt
linkgrid_x_transaction_id-1.0.1.dist-info/RECORD
