Metadata-Version: 2.4
Name: linkgrid-x-transaction-id
Version: 1.0.1
Summary: Twitter X-Client-Transaction-Id generator written in python.
Home-page: https://github.com/OfficialDeepSaha/Transaction-ID-Generator
Author: Deep Saha
Author-email: hiremeasadeveloper@gmail.com
License: MIT
Keywords: x-transaction-id,twitter transaction id,client transaction id twitter,tid generator,x client transaction id generator,xid twitter,twitter api
Classifier: Development Status :: 5 - Production/Stable
Classifier: Intended Audience :: Developers
Classifier: License :: OSI Approved :: MIT License
Classifier: Programming Language :: Python :: 3
Classifier: Programming Language :: Python :: 3.7
Classifier: Programming Language :: Python :: 3.8
Classifier: Programming Language :: Python :: 3.9
Classifier: Programming Language :: Python :: 3.10
Classifier: Programming Language :: Python :: 3.11
Classifier: Operating System :: OS Independent
Requires-Python: >=3.7
License-File: LICENSE
Requires-Dist: beautifulsoup4>=4.9.3
Requires-Dist: requests>=2.25.1
Requires-Dist: aiohttp>=3.8.0
Dynamic: author
Dynamic: author-email
Dynamic: classifier
Dynamic: description
Dynamic: description-content-type
Dynamic: home-page
Dynamic: keywords
Dynamic: license
Dynamic: license-file
Dynamic: requires-dist
Dynamic: requires-python
Dynamic: summary
